{
  "image_file": "1961ca4a-f4a9-4aa2-8e56-15820a786043.png",
  "model": "CV Only (Baseline)",
  "data_points": [
    {
      "label": {
        "lineName": "Cetuximab_500mg_Low"
      },
      "points": [
        {
          "x": 138.01641404206714,
          "y": 82.1930332314206,
          "topBarPixelDistance": 46.0,
          "bottomBarPixelDistance": 7.0,
          "deviationPixelDistance": 46.0,
          "label": ""
        },
        {
          "x": 205.37434940911396,
          "y": 164.18016297704838,
          "topBarPixelDistance": 3.0,
          "bottomBarPixelDistance": 49.0,
          "deviationPixelDistance": 49.0,
          "label": ""
        },
        {
          "x": 353.0945836828508,
          "y": 289.0049064079655,
          "topBarPixelDistance": 50.0,
          "bottomBarPixelDistance": 7.0,
          "deviationPixelDistance": 50.0,
          "label": ""
        },
        {
          "x": 455.93244964690126,
          "y": 344.69815568337606,
          "topBarPixelDistance": 2.0,
          "bottomBarPixelDistance": 31.0,
          "deviationPixelDistance": 31.0,
          "label": ""
        },
        {
          "x": 601.0374847376481,
          "y": 395.8260950829708,
          "topBarPixelDistance": 26.0,
          "bottomBarPixelDistance": 6.0,
          "deviationPixelDistance": 26.0,
          "label": ""
        },
        {
          "x": 620.1249270865112,
          "y": 400.81431662862343,
          "topBarPixelDistance": 32.0,
          "bottomBarPixelDistance": 6.0,
          "deviationPixelDistance": 32.0,
          "label": ""
        }
      ]
    }
  ]
}