{
  "image_file": "5cdd38bc-50f4-44c9-a5c7-86afeb1ca4c9.png",
  "model": "CV Only (Baseline)",
  "data_points": [
    {
      "label": {
        "lineName": "Durvalumab_100mg_TrtA"
      },
      "points": [
        {
          "x": 138.48825769796517,
          "y": 84.68385118536293,
          "topBarPixelDistance": 5.0,
          "bottomBarPixelDistance": 36.0,
          "deviationPixelDistance": 36.0,
          "label": ""
        },
        {
          "x": 173.27953750417907,
          "y": 156.9724515654902,
          "topBarPixelDistance": 50.0,
          "bottomBarPixelDistance": 49.0,
          "deviationPixelDistance": 50.0,
          "label": ""
        },
        {
          "x": 317.410964503004,
          "y": 325.2619931950777,
          "topBarPixelDistance": 32.0,
          "bottomBarPixelDistance": 29.0,
          "deviationPixelDistance": 32.0,
          "label": ""
        },
        {
          "x": 359.75705360305096,
          "y": 348.72664206822003,
          "topBarPixelDistance": 19.0,
          "bottomBarPixelDistance": 4.0,
          "deviationPixelDistance": 19.0,
          "label": ""
        },
        {
          "x": 459.11281934145285,
          "y": 381.58946411115784,
          "topBarPixelDistance": 4.0,
          "bottomBarPixelDistance": 49.0,
          "deviationPixelDistance": 49.0,
          "label": ""
        },
        {
          "x": 547.16485847291,
          "y": 395.8700406158738,
          "topBarPixelDistance": 4.0,
          "bottomBarPixelDistance": 49.0,
          "deviationPixelDistance": 49.0,
          "label": ""
        },
        {
          "x": 608.6925510589523,
          "y": 401.4896074854571,
          "topBarPixelDistance": 50.0,
          "bottomBarPixelDistance": 49.0,
          "deviationPixelDistance": 50.0,
          "label": ""
        },
        {
          "x": 616.6759710193434,
          "y": 402.0455026256838,
          "topBarPixelDistance": 50.0,
          "bottomBarPixelDistance": 49.0,
          "deviationPixelDistance": 50.0,
          "label": ""
        }
      ]
    },
    {
      "label": {
        "lineName": "Infliximab_50mg_QW"
      },
      "points": [
        {
          "x": 77.66096055728927,
          "y": 354.6206375149296,
          "topBarPixelDistance": 3.0,
          "bottomBarPixelDistance": 49.0,
          "deviationPixelDistance": 49.0,
          "label": ""
        },
        {
          "x": 123.26812837401468,
          "y": 298.58528135387553,
          "topBarPixelDistance": 3.0,
          "bottomBarPixelDistance": 49.0,
          "deviationPixelDistance": 49.0,
          "label": ""
        },
        {
          "x": 159.02977217414633,
          "y": 303.69368889589333,
          "topBarPixelDistance": 3.0,
          "bottomBarPixelDistance": 49.0,
          "deviationPixelDistance": 49.0,
          "label": ""
        },
        {
          "x": 216.74585868444856,
          "y": 333.2593147444885,
          "topBarPixelDistance": 2.0,
          "bottomBarPixelDistance": 49.0,
          "deviationPixelDistance": 49.0,
          "label": ""
        },
        {
          "x": 250.7146399357337,
          "y": 350.9574585764101,
          "topBarPixelDistance": 6.0,
          "bottomBarPixelDistance": 49.0,
          "deviationPixelDistance": 49.0,
          "label": ""
        },
        {
          "x": 251.26237806800114,
          "y": 351.2252102412517,
          "topBarPixelDistance": 7.0,
          "bottomBarPixelDistance": 49.0,
          "deviationPixelDistance": 49.0,
          "label": ""
        },
        {
          "x": 267.4324113878819,
          "y": 358.8280111601667,
          "topBarPixelDistance": 4.0,
          "bottomBarPixelDistance": 32.0,
          "deviationPixelDistance": 32.0,
          "label": ""
        },
        {
          "x": 309.1339646647488,
          "y": 375.6276375442865,
          "topBarPixelDistance": 47.0,
          "bottomBarPixelDistance": 49.0,
          "deviationPixelDistance": 49.0,
          "label": ""
        }
      ]
    }
  ]
}