{
  "image_file": "bb24697f-9d40-4d95-98f3-3e9a175a713f.png",
  "model": "CV Only (Baseline)",
  "data_points": [
    {
      "label": {
        "lineName": "CRP_TrtB"
      },
      "points": [
        {
          "x": 225.25784446230713,
          "y": 82.95278540106983,
          "topBarPixelDistance": 2.0,
          "bottomBarPixelDistance": 49.0,
          "deviationPixelDistance": 49.0,
          "label": ""
        },
        {
          "x": 382.57842824254493,
          "y": 60.156703903175526,
          "topBarPixelDistance": 3.0,
          "bottomBarPixelDistance": 49.0,
          "deviationPixelDistance": 49.0,
          "label": ""
        },
        {
          "x": 432.7866391358025,
          "y": 58.87176926329005,
          "topBarPixelDistance": 45.0,
          "bottomBarPixelDistance": 49.0,
          "deviationPixelDistance": 49.0,
          "label": ""
        },
        {
          "x": 445.3236821263496,
          "y": 58.67461319766949,
          "topBarPixelDistance": 3.0,
          "bottomBarPixelDistance": 49.0,
          "deviationPixelDistance": 49.0,
          "label": ""
        },
        {
          "x": 449.2202923912903,
          "y": 58.620438281158954,
          "topBarPixelDistance": 2.0,
          "bottomBarPixelDistance": 49.0,
          "deviationPixelDistance": 49.0,
          "label": ""
        },
        {
          "x": 555.459302369045,
          "y": 57.89832992625338,
          "topBarPixelDistance": 2.0,
          "bottomBarPixelDistance": 49.0,
          "deviationPixelDistance": 49.0,
          "label": ""
        },
        {
          "x": 614.3020229120158,
          "y": 57.78871343611911,
          "topBarPixelDistance": 2.0,
          "bottomBarPixelDistance": 49.0,
          "deviationPixelDistance": 49.0,
          "label": ""
        },
        {
          "x": 645.6787760783902,
          "y": 57.75944668604643,
          "topBarPixelDistance": 44.0,
          "bottomBarPixelDistance": 49.0,
          "deviationPixelDistance": 49.0,
          "label": ""
        }
      ]
    },
    {
      "label": {
        "lineName": "WBC_Control"
      },
      "points": [
        {
          "x": 89.82340070417737,
          "y": 402.80791469943574,
          "topBarPixelDistance": 32.0,
          "bottomBarPixelDistance": 42.0,
          "deviationPixelDistance": 42.0,
          "label": ""
        },
        {
          "x": 131.97403192232468,
          "y": 326.88590343160024,
          "topBarPixelDistance": 27.0,
          "bottomBarPixelDistance": 49.0,
          "deviationPixelDistance": 49.0,
          "label": ""
        },
        {
          "x": 226.3520502197337,
          "y": 208.54881781416907,
          "topBarPixelDistance": 50.0,
          "bottomBarPixelDistance": 49.0,
          "deviationPixelDistance": 50.0,
          "label": ""
        },
        {
          "x": 293.8003819348678,
          "y": 94.5072101127264,
          "topBarPixelDistance": 50.0,
          "bottomBarPixelDistance": 49.0,
          "deviationPixelDistance": 50.0,
          "label": ""
        }
      ]
    }
  ]
}