{
  "image_file": "eed17b3b-5f5a-4879-8bb6-c51a71401a5e.png",
  "model": "CV Only (Baseline)",
  "data_points": [
    {
      "label": {
        "lineName": "Bevacizumab_0.1mg_kg_TrtA"
      },
      "points": [
        {
          "x": 104.10016363691733,
          "y": 391.2243999845079,
          "topBarPixelDistance": 50.0,
          "bottomBarPixelDistance": 13.0,
          "deviationPixelDistance": 50.0,
          "label": ""
        },
        {
          "x": 249.63646966794292,
          "y": 63.97527115838648,
          "topBarPixelDistance": 50.0,
          "bottomBarPixelDistance": 49.0,
          "deviationPixelDistance": 50.0,
          "label": ""
        },
        {
          "x": 281.05869781985325,
          "y": 62.348153282585486,
          "topBarPixelDistance": 3.0,
          "bottomBarPixelDistance": 49.0,
          "deviationPixelDistance": 49.0,
          "label": ""
        },
        {
          "x": 458.5249976192431,
          "y": 192.1112562111923,
          "topBarPixelDistance": 45.0,
          "bottomBarPixelDistance": 49.0,
          "deviationPixelDistance": 49.0,
          "label": ""
        },
        {
          "x": 619.0420750261057,
          "y": 346.45654167789695,
          "topBarPixelDistance": 50.0,
          "bottomBarPixelDistance": 24.0,
          "deviationPixelDistance": 50.0,
          "label": ""
        },
        {
          "x": 646.9522830959893,
          "y": 370.59911104938783,
          "topBarPixelDistance": 0.0,
          "bottomBarPixelDistance": 0.0,
          "deviationPixelDistance": 0.0,
          "label": ""
        }
      ]
    }
  ]
}