{
  "image_file": "5f5e9c03-1160-4de7-9191-a7ea062bfc1b.png",
  "model": "VQA-4bit-Fast",
  "error_bars": [
    {
      "lineName": "Pembrolizumab_500mg_TrtB",
      "points": [
        {
          "data_point": {
            "x": 100.37230683323868,
            "y": 87.58314445827347
          },
          "upper_error_bar": {
            "x": 100.37230683323868,
            "y": 87.58314445827347
          },
          "lower_error_bar": {
            "x": 100.37230683323868,
            "y": 87.58314445827347
          }
        },
        {
          "data_point": {
            "x": 139.79668356887998,
            "y": 160.21782680046556
          },
          "upper_error_bar": {
            "x": 139.79668356887998,
            "y": 71.0
          },
          "lower_error_bar": {
            "x": 139.79668356887998,
            "y": 170.43565360093112
          }
        },
        {
          "data_point": {
            "x": 195.3514150596189,
            "y": 244.74358135095648
          },
          "upper_error_bar": {
            "x": 195.3514150596189,
            "y": 244.74358135095648
          },
          "lower_error_bar": {
            "x": 195.3514150596189,
            "y": 244.74358135095648
          }
        },
        {
          "data_point": {
            "x": 210.00907265780745,
            "y": 262.46024976736066
          },
          "upper_error_bar": {
            "x": 210.00907265780745,
            "y": 262.46024976736066
          },
          "lower_error_bar": {
            "x": 210.00907265780745,
            "y": 262.46024976736066
          }
        },
        {
          "data_point": {
            "x": 511.28826573410686,
            "y": 397.44068151067853
          },
          "upper_error_bar": {
            "x": 511.28826573410686,
            "y": 397.44068151067853
          },
          "lower_error_bar": {
            "x": 511.28826573410686,
            "y": 397.44068151067853
          }
        }
      ]
    },
    {
      "lineName": "Daratumumab_1mg_kg_Q4W",
      "points": [
        {
          "data_point": {
            "x": 310.17603954149047,
            "y": 275.35313171745236
          },
          "upper_error_bar": {
            "x": 310.17603954149047,
            "y": 275.35313171745236
          },
          "lower_error_bar": {
            "x": 310.17603954149047,
            "y": 275.35313171745236
          }
        },
        {
          "data_point": {
            "x": 326.103416968491,
            "y": 287.17795733315387
          },
          "upper_error_bar": {
            "x": 326.103416968491,
            "y": 287.17795733315387
          },
          "lower_error_bar": {
            "x": 326.103416968491,
            "y": 287.17795733315387
          }
        },
        {
          "data_point": {
            "x": 359.92123736565304,
            "y": 309.27103622099736
          },
          "upper_error_bar": {
            "x": 359.92123736565304,
            "y": 233.0
          },
          "lower_error_bar": {
            "x": 359.92123736565304,
            "y": 355.5420724419947
          }
        },
        {
          "data_point": {
            "x": 410.8081014424456,
            "y": 336.00257319803904
          },
          "upper_error_bar": {
            "x": 410.8081014424456,
            "y": 336.00257319803904
          },
          "lower_error_bar": {
            "x": 410.8081014424456,
            "y": 336.00257319803904
          }
        },
        {
          "data_point": {
            "x": 554.9390724766134,
            "y": 382.58755426686247
          },
          "upper_error_bar": {
            "x": 554.9390724766134,
            "y": 382.58755426686247
          },
          "lower_error_bar": {
            "x": 554.9390724766134,
            "y": 382.58755426686247
          }
        },
        {
          "data_point": {
            "x": 576.7631474824242,
            "y": 387.0705177571964
          },
          "upper_error_bar": {
            "x": 576.7631474824242,
            "y": 387.0705177571964
          },
          "lower_error_bar": {
            "x": 576.7631474824242,
            "y": 387.0705177571964
          }
        },
        {
          "data_point": {
            "x": 578.4697921002204,
            "y": 387.4001462585285
          },
          "upper_error_bar": {
            "x": 578.4697921002204,
            "y": 387.4001462585285
          },
          "lower_error_bar": {
            "x": 578.4697921002204,
            "y": 387.4001462585285
          }
        },
        {
          "data_point": {
            "x": 633.036349092251,
            "y": 396.53795396957315
          },
          "upper_error_bar": {
            "x": 633.036349092251,
            "y": 396.53795396957315
          },
          "lower_error_bar": {
            "x": 633.036349092251,
            "y": 396.53795396957315
          }
        },
        {
          "data_point": {
            "x": 652.1781616584375,
            "y": 399.1777120424249
          },
          "upper_error_bar": {
            "x": 652.1781616584375,
            "y": 399.1777120424249
          },
          "lower_error_bar": {
            "x": 652.1781616584375,
            "y": 399.1777120424249
          }
        }
      ]
    }
  ]
}