{
  "image_file": "871fc94b-d60e-4b09-80c6-29bfbd0bb522.png",
  "model": "VQA-4bit-Fast",
  "error_bars": [
    {
      "lineName": "IL-6_Mid",
      "points": [
        {
          "data_point": {
            "x": 101.37062589717124,
            "y": 393.05768300439934
          },
          "upper_error_bar": {
            "x": 101.37062589717124,
            "y": 270.0
          },
          "lower_error_bar": {
            "x": 101.37062589717124,
            "y": 415.1153660087987
          }
        },
        {
          "data_point": {
            "x": 175.35622741917095,
            "y": 184.8510277886071
          },
          "upper_error_bar": {
            "x": 175.35622741917095,
            "y": 181.0
          },
          "lower_error_bar": {
            "x": 175.35622741917095,
            "y": 365.0
          }
        },
        {
          "data_point": {
            "x": 500.34432329956695,
            "y": 93.61152270553862
          },
          "upper_error_bar": {
            "x": 500.34432329956695,
            "y": 38.0
          },
          "lower_error_bar": {
            "x": 500.34432329956695,
            "y": 266.0
          }
        },
        {
          "data_point": {
            "x": 557.453841622931,
            "y": 93.30930750481934
          },
          "upper_error_bar": {
            "x": 557.453841622931,
            "y": 38.0
          },
          "lower_error_bar": {
            "x": 557.453841622931,
            "y": 105.61861500963869
          }
        },
        {
          "data_point": {
            "x": 604.7099644560856,
            "y": 93.20203527297076
          },
          "upper_error_bar": {
            "x": 604.7099644560856,
            "y": 38.0
          },
          "lower_error_bar": {
            "x": 604.7099644560856,
            "y": 105.40407054594152
          }
        },
        {
          "data_point": {
            "x": 643.9070194878213,
            "y": 93.1578281732975
          },
          "upper_error_bar": {
            "x": 643.9070194878213,
            "y": 89.0
          },
          "lower_error_bar": {
            "x": 643.9070194878213,
            "y": 390.0
          }
        }
      ]
    }
  ]
}