{
  "image_file": "96ba61fa-bbf1-4a8a-bfb4-b8f71b8ca771.png",
  "model": "VQA-4bit-Fast",
  "error_bars": [
    {
      "lineName": "Nivolumab_3mg_kg_multi",
      "points": [
        {
          "data_point": {
            "x": 135.3141786870717,
            "y": 59.04962392075936
          },
          "upper_error_bar": {
            "x": 135.3141786870717,
            "y": 59.04962392075936
          },
          "lower_error_bar": {
            "x": 135.3141786870717,
            "y": 59.04962392075936
          }
        },
        {
          "data_point": {
            "x": 197.14286824054682,
            "y": 88.85790195890877
          },
          "upper_error_bar": {
            "x": 197.14286824054682,
            "y": 10.0
          },
          "lower_error_bar": {
            "x": 197.14286824054682,
            "y": 99.71580391781754
          }
        },
        {
          "data_point": {
            "x": 209.4161880193265,
            "y": 101.9884780272929
          },
          "upper_error_bar": {
            "x": 209.4161880193265,
            "y": 10.0
          },
          "lower_error_bar": {
            "x": 209.4161880193265,
            "y": 112.9769560545858
          }
        },
        {
          "data_point": {
            "x": 230.4105122814169,
            "y": 125.15308272817236
          },
          "upper_error_bar": {
            "x": 230.4105122814169,
            "y": 117.30616545634473
          },
          "lower_error_bar": {
            "x": 230.4105122814169,
            "y": 233.0
          }
        },
        {
          "data_point": {
            "x": 334.6807452618573,
            "y": 229.42293115499393
          },
          "upper_error_bar": {
            "x": 334.6807452618573,
            "y": 229.42293115499393
          },
          "lower_error_bar": {
            "x": 334.6807452618573,
            "y": 229.42293115499393
          }
        },
        {
          "data_point": {
            "x": 351.81131826950985,
            "y": 243.92647232861395
          },
          "upper_error_bar": {
            "x": 351.81131826950985,
            "y": 243.92647232861395
          },
          "lower_error_bar": {
            "x": 351.81131826950985,
            "y": 243.92647232861395
          }
        },
        {
          "data_point": {
            "x": 483.888233776224,
            "y": 333.87978121049287
          },
          "upper_error_bar": {
            "x": 483.888233776224,
            "y": 333.87978121049287
          },
          "lower_error_bar": {
            "x": 483.888233776224,
            "y": 333.87978121049287
          }
        },
        {
          "data_point": {
            "x": 618.8555540682706,
            "y": 395.2780423774247
          },
          "upper_error_bar": {
            "x": 618.8555540682706,
            "y": 395.2780423774247
          },
          "lower_error_bar": {
            "x": 618.8555540682706,
            "y": 395.2780423774247
          }
        }
      ]
    }
  ]
}