{
  "image_file": "98454074-e0e6-4170-a243-99aba875a1d8.png",
  "model": "VQA-4bit-Fast",
  "error_bars": [
    {
      "lineName": "Atezolizumab_0.1mg_kg_Mid",
      "points": [
        {
          "data_point": {
            "x": 119.3338958173716,
            "y": 318.9681966371036
          },
          "upper_error_bar": {
            "x": 119.3338958173716,
            "y": 318.9681966371036
          },
          "lower_error_bar": {
            "x": 119.3338958173716,
            "y": 318.9681966371036
          }
        },
        {
          "data_point": {
            "x": 136.3281381833798,
            "y": 316.89383890232483
          },
          "upper_error_bar": {
            "x": 136.3281381833798,
            "y": 12.0
          },
          "lower_error_bar": {
            "x": 136.3281381833798,
            "y": 483.78767780464966
          }
        },
        {
          "data_point": {
            "x": 173.70062269248905,
            "y": 331.6356005462915
          },
          "upper_error_bar": {
            "x": 173.70062269248905,
            "y": 52.0
          },
          "lower_error_bar": {
            "x": 173.70062269248905,
            "y": 474.27120109258306
          }
        },
        {
          "data_point": {
            "x": 195.3034522007493,
            "y": 343.2343713743146
          },
          "upper_error_bar": {
            "x": 195.3034522007493,
            "y": 343.2343713743146
          },
          "lower_error_bar": {
            "x": 195.3034522007493,
            "y": 343.2343713743146
          }
        },
        {
          "data_point": {
            "x": 306.31547746125136,
            "y": 387.5307676749388
          },
          "upper_error_bar": {
            "x": 306.31547746125136,
            "y": 387.5307676749388
          },
          "lower_error_bar": {
            "x": 306.31547746125136,
            "y": 387.5307676749388
          }
        },
        {
          "data_point": {
            "x": 315.83736439713107,
            "y": 389.9238844791562
          },
          "upper_error_bar": {
            "x": 315.83736439713107,
            "y": 389.9238844791562
          },
          "lower_error_bar": {
            "x": 315.83736439713107,
            "y": 389.9238844791562
          }
        },
        {
          "data_point": {
            "x": 390.80725389017545,
            "y": 403.5324727666245
          },
          "upper_error_bar": {
            "x": 390.80725389017545,
            "y": 403.5324727666245
          },
          "lower_error_bar": {
            "x": 390.80725389017545,
            "y": 403.5324727666245
          }
        },
        {
          "data_point": {
            "x": 417.25849554553344,
            "y": 406.6685697507392
          },
          "upper_error_bar": {
            "x": 417.25849554553344,
            "y": 406.6685697507392
          },
          "lower_error_bar": {
            "x": 417.25849554553344,
            "y": 406.6685697507392
          }
        },
        {
          "data_point": {
            "x": 443.0322031164681,
            "y": 409.1369527046188
          },
          "upper_error_bar": {
            "x": 443.0322031164681,
            "y": 409.1369527046188
          },
          "lower_error_bar": {
            "x": 443.0322031164681,
            "y": 409.1369527046188
          }
        },
        {
          "data_point": {
            "x": 479.0535518800033,
            "y": 411.8211372470181
          },
          "upper_error_bar": {
            "x": 479.0535518800033,
            "y": 411.8211372470181
          },
          "lower_error_bar": {
            "x": 479.0535518800033,
            "y": 411.8211372470181
          }
        },
        {
          "data_point": {
            "x": 483.67472562347024,
            "y": 412.11170710825706
          },
          "upper_error_bar": {
            "x": 483.67472562347024,
            "y": 412.11170710825706
          },
          "lower_error_bar": {
            "x": 483.67472562347024,
            "y": 412.11170710825706
          }
        },
        {
          "data_point": {
            "x": 503.4285171661279,
            "y": 413.2370387372143
          },
          "upper_error_bar": {
            "x": 503.4285171661279,
            "y": 413.2370387372143
          },
          "lower_error_bar": {
            "x": 503.4285171661279,
            "y": 413.2370387372143
          }
        },
        {
          "data_point": {
            "x": 513.8070751298987,
            "y": 413.7592846551741
          },
          "upper_error_bar": {
            "x": 513.8070751298987,
            "y": 413.7592846551741
          },
          "lower_error_bar": {
            "x": 513.8070751298987,
            "y": 413.7592846551741
          }
        }
      ]
    },
    {
      "lineName": "Ipilimumab_50mg_TrtB",
      "points": [
        {
          "data_point": {
            "x": 92.20524222928348,
            "y": 290.17187420373756
          },
          "upper_error_bar": {
            "x": 92.20524222928348,
            "y": 290.17187420373756
          },
          "lower_error_bar": {
            "x": 92.20524222928348,
            "y": 290.17187420373756
          }
        },
        {
          "data_point": {
            "x": 206.31382976837057,
            "y": 307.8380254246242
          },
          "upper_error_bar": {
            "x": 206.31382976837057,
            "y": 307.8380254246242
          },
          "lower_error_bar": {
            "x": 206.31382976837057,
            "y": 307.8380254246242
          }
        },
        {
          "data_point": {
            "x": 211.02812105984822,
            "y": 311.64664439803164
          },
          "upper_error_bar": {
            "x": 211.02812105984822,
            "y": 311.64664439803164
          },
          "lower_error_bar": {
            "x": 211.02812105984822,
            "y": 311.64664439803164
          }
        },
        {
          "data_point": {
            "x": 219.78556507503478,
            "y": 318.40287379557134
          },
          "upper_error_bar": {
            "x": 219.78556507503478,
            "y": 130.0
          },
          "lower_error_bar": {
            "x": 219.78556507503478,
            "y": 388.8057475911427
          }
        },
        {
          "data_point": {
            "x": 299.17075067479095,
            "y": 363.09892848873596
          },
          "upper_error_bar": {
            "x": 299.17075067479095,
            "y": 363.09892848873596
          },
          "lower_error_bar": {
            "x": 299.17075067479095,
            "y": 363.09892848873596
          }
        },
        {
          "data_point": {
            "x": 313.60407228020324,
            "y": 368.66399171483636
          },
          "upper_error_bar": {
            "x": 313.60407228020324,
            "y": 368.66399171483636
          },
          "lower_error_bar": {
            "x": 313.60407228020324,
            "y": 368.66399171483636
          }
        },
        {
          "data_point": {
            "x": 386.4604668106725,
            "y": 388.87420490122804
          },
          "upper_error_bar": {
            "x": 386.4604668106725,
            "y": 388.87420490122804
          },
          "lower_error_bar": {
            "x": 386.4604668106725,
            "y": 388.87420490122804
          }
        },
        {
          "data_point": {
            "x": 393.9530638475866,
            "y": 390.3702419241677
          },
          "upper_error_bar": {
            "x": 393.9530638475866,
            "y": 390.3702419241677
          },
          "lower_error_bar": {
            "x": 393.9530638475866,
            "y": 390.3702419241677
          }
        },
        {
          "data_point": {
            "x": 403.27021569930537,
            "y": 392.11191979854715
          },
          "upper_error_bar": {
            "x": 403.27021569930537,
            "y": 392.11191979854715
          },
          "lower_error_bar": {
            "x": 403.27021569930537,
            "y": 392.11191979854715
          }
        },
        {
          "data_point": {
            "x": 630.0125281637563,
            "y": 411.19055348406556
          },
          "upper_error_bar": {
            "x": 630.0125281637563,
            "y": 411.19055348406556
          },
          "lower_error_bar": {
            "x": 630.0125281637563,
            "y": 411.19055348406556
          }
        }
      ]
    },
    {
      "lineName": "Trastuzumab_50mg_Q2W",
      "points": [
        {
          "data_point": {
            "x": 106.39571374844999,
            "y": 91.05731662579848
          },
          "upper_error_bar": {
            "x": 106.39571374844999,
            "y": 91.05731662579848
          },
          "lower_error_bar": {
            "x": 106.39571374844999,
            "y": 91.05731662579848
          }
        },
        {
          "data_point": {
            "x": 110.34137476589424,
            "y": 80.68766337892237
          },
          "upper_error_bar": {
            "x": 110.34137476589424,
            "y": 80.68766337892237
          },
          "lower_error_bar": {
            "x": 110.34137476589424,
            "y": 80.68766337892237
          }
        },
        {
          "data_point": {
            "x": 148.0610794393465,
            "y": 79.3809826362932
          },
          "upper_error_bar": {
            "x": 148.0610794393465,
            "y": 56.0
          },
          "lower_error_bar": {
            "x": 148.0610794393465,
            "y": 172.0
          }
        },
        {
          "data_point": {
            "x": 149.2203020260983,
            "y": 80.53035548104947
          },
          "upper_error_bar": {
            "x": 149.2203020260983,
            "y": 56.0
          },
          "lower_error_bar": {
            "x": 149.2203020260983,
            "y": 172.0
          }
        },
        {
          "data_point": {
            "x": 154.70586400366216,
            "y": 86.26533262719994
          },
          "upper_error_bar": {
            "x": 154.70586400366216,
            "y": 56.0
          },
          "lower_error_bar": {
            "x": 154.70586400366216,
            "y": 172.0
          }
        },
        {
          "data_point": {
            "x": 165.38452863609587,
            "y": 98.3277591211986
          },
          "upper_error_bar": {
            "x": 165.38452863609587,
            "y": 98.3277591211986
          },
          "lower_error_bar": {
            "x": 165.38452863609587,
            "y": 98.3277591211986
          }
        },
        {
          "data_point": {
            "x": 180.7438605322422,
            "y": 116.39992349252572
          },
          "upper_error_bar": {
            "x": 180.7438605322422,
            "y": 52.0
          },
          "lower_error_bar": {
            "x": 180.7438605322422,
            "y": 189.0
          }
        },
        {
          "data_point": {
            "x": 234.78814208225563,
            "y": 175.5594640386464
          },
          "upper_error_bar": {
            "x": 234.78814208225563,
            "y": 130.0
          },
          "lower_error_bar": {
            "x": 234.78814208225563,
            "y": 248.0
          }
        },
        {
          "data_point": {
            "x": 247.4024910235913,
            "y": 187.75171152216336
          },
          "upper_error_bar": {
            "x": 247.4024910235913,
            "y": 187.75171152216336
          },
          "lower_error_bar": {
            "x": 247.4024910235913,
            "y": 187.75171152216336
          }
        },
        {
          "data_point": {
            "x": 261.6112181003157,
            "y": 200.75009781416907
          },
          "upper_error_bar": {
            "x": 261.6112181003157,
            "y": 200.75009781416907
          },
          "lower_error_bar": {
            "x": 261.6112181003157,
            "y": 200.75009781416907
          }
        },
        {
          "data_point": {
            "x": 283.93183253358444,
            "y": 219.68163391322776
          },
          "upper_error_bar": {
            "x": 283.93183253358444,
            "y": 219.68163391322776
          },
          "lower_error_bar": {
            "x": 283.93183253358444,
            "y": 219.68163391322776
          }
        },
        {
          "data_point": {
            "x": 328.93649273673384,
            "y": 252.87772066494068
          },
          "upper_error_bar": {
            "x": 328.93649273673384,
            "y": 252.87772066494068
          },
          "lower_error_bar": {
            "x": 328.93649273673384,
            "y": 252.87772066494068
          }
        },
        {
          "data_point": {
            "x": 383.50603891399345,
            "y": 285.57117247393774
          },
          "upper_error_bar": {
            "x": 383.50603891399345,
            "y": 285.57117247393774
          },
          "lower_error_bar": {
            "x": 383.50603891399345,
            "y": 285.57117247393774
          }
        },
        {
          "data_point": {
            "x": 403.8534741412353,
            "y": 295.97031493538327
          },
          "upper_error_bar": {
            "x": 403.8534741412353,
            "y": 295.97031493538327
          },
          "lower_error_bar": {
            "x": 403.8534741412353,
            "y": 295.97031493538327
          }
        }
      ]
    },
    {
      "lineName": "Bevacizumab_3mg_kg_single",
      "points": [
        {
          "data_point": {
            "x": 167.6022411917456,
            "y": 92.18583449304015
          },
          "upper_error_bar": {
            "x": 167.6022411917456,
            "y": 92.18583449304015
          },
          "lower_error_bar": {
            "x": 167.6022411917456,
            "y": 92.18583449304015
          }
        },
        {
          "data_point": {
            "x": 189.62514216302708,
            "y": 126.85672263247432
          },
          "upper_error_bar": {
            "x": 189.62514216302708,
            "y": 126.85672263247432
          },
          "lower_error_bar": {
            "x": 189.62514216302708,
            "y": 126.85672263247432
          }
        },
        {
          "data_point": {
            "x": 208.04171362750657,
            "y": 155.47060506363317
          },
          "upper_error_bar": {
            "x": 208.04171362750657,
            "y": 155.47060506363317
          },
          "lower_error_bar": {
            "x": 208.04171362750657,
            "y": 155.47060506363317
          }
        },
        {
          "data_point": {
            "x": 233.34065996182633,
            "y": 191.64672291188424
          },
          "upper_error_bar": {
            "x": 233.34065996182633,
            "y": 130.0
          },
          "lower_error_bar": {
            "x": 233.34065996182633,
            "y": 248.0
          }
        },
        {
          "data_point": {
            "x": 353.0765057899393,
            "y": 307.8889777939108
          },
          "upper_error_bar": {
            "x": 353.0765057899393,
            "y": 307.8889777939108
          },
          "lower_error_bar": {
            "x": 353.0765057899393,
            "y": 307.8889777939108
          }
        },
        {
          "data_point": {
            "x": 362.05345206616636,
            "y": 313.6787354574307
          },
          "upper_error_bar": {
            "x": 362.05345206616636,
            "y": 313.6787354574307
          },
          "lower_error_bar": {
            "x": 362.05345206616636,
            "y": 313.6787354574307
          }
        },
        {
          "data_point": {
            "x": 377.5242065879888,
            "y": 322.9413311966586
          },
          "upper_error_bar": {
            "x": 377.5242065879888,
            "y": 322.9413311966586
          },
          "lower_error_bar": {
            "x": 377.5242065879888,
            "y": 322.9413311966586
          }
        },
        {
          "data_point": {
            "x": 380.3477863566018,
            "y": 324.5394070131106
          },
          "upper_error_bar": {
            "x": 380.3477863566018,
            "y": 324.5394070131106
          },
          "lower_error_bar": {
            "x": 380.3477863566018,
            "y": 324.5394070131106
          }
        },
        {
          "data_point": {
            "x": 381.6247211552944,
            "y": 325.2531160729837
          },
          "upper_error_bar": {
            "x": 381.6247211552944,
            "y": 325.2531160729837
          },
          "lower_error_bar": {
            "x": 381.6247211552944,
            "y": 325.2531160729837
          }
        }
      ]
    }
  ]
}