{
  "image_file": "bde44276-688c-41a3-bed4-3e653a322530.png",
  "model": "VQA-4bit-Fast",
  "error_bars": [
    {
      "lineName": "Vanucizumab_100mg_QD",
      "points": [
        {
          "data_point": {
            "x": 143.1258685457446,
            "y": 133.27879812356719
          },
          "upper_error_bar": {
            "x": 143.1258685457446,
            "y": 133.0
          },
          "lower_error_bar": {
            "x": 143.1258685457446,
            "y": 214.0
          }
        },
        {
          "data_point": {
            "x": 207.68040626491018,
            "y": 219.11153133586896
          },
          "upper_error_bar": {
            "x": 207.68040626491018,
            "y": 10.0
          },
          "lower_error_bar": {
            "x": 207.68040626491018,
            "y": 260.0
          }
        },
        {
          "data_point": {
            "x": 228.7328249180918,
            "y": 248.28825734338452
          },
          "upper_error_bar": {
            "x": 228.7328249180918,
            "y": 248.28825734338452
          },
          "lower_error_bar": {
            "x": 228.7328249180918,
            "y": 248.28825734338452
          }
        },
        {
          "data_point": {
            "x": 278.14753965568406,
            "y": 304.7413894139278
          },
          "upper_error_bar": {
            "x": 278.14753965568406,
            "y": 304.7413894139278
          },
          "lower_error_bar": {
            "x": 278.14753965568406,
            "y": 304.7413894139278
          }
        },
        {
          "data_point": {
            "x": 289.32400682465084,
            "y": 315.05106128639915
          },
          "upper_error_bar": {
            "x": 289.32400682465084,
            "y": 315.05106128639915
          },
          "lower_error_bar": {
            "x": 289.32400682465084,
            "y": 315.05106128639915
          }
        },
        {
          "data_point": {
            "x": 311.8288771028698,
            "y": 333.30476557594295
          },
          "upper_error_bar": {
            "x": 311.8288771028698,
            "y": 333.30476557594295
          },
          "lower_error_bar": {
            "x": 311.8288771028698,
            "y": 333.30476557594295
          }
        },
        {
          "data_point": {
            "x": 312.898631262352,
            "y": 334.0942460079064
          },
          "upper_error_bar": {
            "x": 312.898631262352,
            "y": 334.0942460079064
          },
          "lower_error_bar": {
            "x": 312.898631262352,
            "y": 334.0942460079064
          }
        },
        {
          "data_point": {
            "x": 317.97218190615564,
            "y": 337.7474198696409
          },
          "upper_error_bar": {
            "x": 317.97218190615564,
            "y": 337.7474198696409
          },
          "lower_error_bar": {
            "x": 317.97218190615564,
            "y": 337.7474198696409
          }
        },
        {
          "data_point": {
            "x": 326.37554258733593,
            "y": 343.4774660973981
          },
          "upper_error_bar": {
            "x": 326.37554258733593,
            "y": 343.4774660973981
          },
          "lower_error_bar": {
            "x": 326.37554258733593,
            "y": 343.4774660973981
          }
        },
        {
          "data_point": {
            "x": 348.6342232515269,
            "y": 356.873514449404
          },
          "upper_error_bar": {
            "x": 348.6342232515269,
            "y": 356.873514449404
          },
          "lower_error_bar": {
            "x": 348.6342232515269,
            "y": 356.873514449404
          }
        },
        {
          "data_point": {
            "x": 410.9624271922526,
            "y": 383.4002984620185
          },
          "upper_error_bar": {
            "x": 410.9624271922526,
            "y": 383.4002984620185
          },
          "lower_error_bar": {
            "x": 410.9624271922526,
            "y": 383.4002984620185
          }
        },
        {
          "data_point": {
            "x": 428.5251395576278,
            "y": 388.6489812080859
          },
          "upper_error_bar": {
            "x": 428.5251395576278,
            "y": 388.6489812080859
          },
          "lower_error_bar": {
            "x": 428.5251395576278,
            "y": 388.6489812080859
          }
        },
        {
          "data_point": {
            "x": 428.81738771767976,
            "y": 388.72975131488994
          },
          "upper_error_bar": {
            "x": 428.81738771767976,
            "y": 388.72975131488994
          },
          "lower_error_bar": {
            "x": 428.81738771767976,
            "y": 388.72975131488994
          }
        }
      ]
    },
    {
      "lineName": "Solanezumab_10mg_kg_Q2W",
      "points": [
        {
          "data_point": {
            "x": 85.89762744563488,
            "y": 206.40811958954112
          },
          "upper_error_bar": {
            "x": 85.89762744563488,
            "y": 98.0
          },
          "lower_error_bar": {
            "x": 85.89762744563488,
            "y": 215.0
          }
        },
        {
          "data_point": {
            "x": 87.31508136192755,
            "y": 195.06415049670028
          },
          "upper_error_bar": {
            "x": 87.31508136192755,
            "y": 98.0
          },
          "lower_error_bar": {
            "x": 87.31508136192755,
            "y": 215.0
          }
        },
        {
          "data_point": {
            "x": 117.89673162238009,
            "y": 60.36291003188711
          },
          "upper_error_bar": {
            "x": 117.89673162238009,
            "y": 10.0
          },
          "lower_error_bar": {
            "x": 117.89673162238009,
            "y": 118.0
          }
        },
        {
          "data_point": {
            "x": 161.82971052924466,
            "y": 50.67391348002701
          },
          "upper_error_bar": {
            "x": 161.82971052924466,
            "y": 0.3478269600540216
          },
          "lower_error_bar": {
            "x": 161.82971052924466,
            "y": 445.0
          }
        },
        {
          "data_point": {
            "x": 206.82941723029336,
            "y": 104.02233021751539
          },
          "upper_error_bar": {
            "x": 206.82941723029336,
            "y": 10.0
          },
          "lower_error_bar": {
            "x": 206.82941723029336,
            "y": 260.0
          }
        },
        {
          "data_point": {
            "x": 331.6529197061471,
            "y": 254.81683365459887
          },
          "upper_error_bar": {
            "x": 331.6529197061471,
            "y": 254.81683365459887
          },
          "lower_error_bar": {
            "x": 331.6529197061471,
            "y": 254.81683365459887
          }
        },
        {
          "data_point": {
            "x": 353.6258965976522,
            "y": 274.8182475519883
          },
          "upper_error_bar": {
            "x": 353.6258965976522,
            "y": 10.0
          },
          "lower_error_bar": {
            "x": 353.6258965976522,
            "y": 445.0
          }
        },
        {
          "data_point": {
            "x": 436.87727127541916,
            "y": 334.9330737014515
          },
          "upper_error_bar": {
            "x": 436.87727127541916,
            "y": 334.9330737014515
          },
          "lower_error_bar": {
            "x": 436.87727127541916,
            "y": 334.9330737014515
          }
        },
        {
          "data_point": {
            "x": 456.07584190323814,
            "y": 345.83937818340553
          },
          "upper_error_bar": {
            "x": 456.07584190323814,
            "y": 283.67875636681106
          },
          "lower_error_bar": {
            "x": 456.07584190323814,
            "y": 458.0
          }
        },
        {
          "data_point": {
            "x": 461.5620089336372,
            "y": 348.7831572687066
          },
          "upper_error_bar": {
            "x": 461.5620089336372,
            "y": 289.5663145374132
          },
          "lower_error_bar": {
            "x": 461.5620089336372,
            "y": 458.0
          }
        },
        {
          "data_point": {
            "x": 538.1491294118644,
            "y": 382.9783173332065
          },
          "upper_error_bar": {
            "x": 538.1491294118644,
            "y": 382.9783173332065
          },
          "lower_error_bar": {
            "x": 538.1491294118644,
            "y": 382.9783173332065
          }
        },
        {
          "data_point": {
            "x": 548.9719722786774,
            "y": 386.90907143028386
          },
          "upper_error_bar": {
            "x": 548.9719722786774,
            "y": 386.90907143028386
          },
          "lower_error_bar": {
            "x": 548.9719722786774,
            "y": 386.90907143028386
          }
        },
        {
          "data_point": {
            "x": 575.9335565996256,
            "y": 395.8892899533339
          },
          "upper_error_bar": {
            "x": 575.9335565996256,
            "y": 10.0
          },
          "lower_error_bar": {
            "x": 575.9335565996256,
            "y": 406.0
          }
        },
        {
          "data_point": {
            "x": 591.918365929257,
            "y": 400.7095257580262
          },
          "upper_error_bar": {
            "x": 591.918365929257,
            "y": 400.7095257580262
          },
          "lower_error_bar": {
            "x": 591.918365929257,
            "y": 400.7095257580262
          }
        },
        {
          "data_point": {
            "x": 610.5105974309422,
            "y": 405.8868453461804
          },
          "upper_error_bar": {
            "x": 610.5105974309422,
            "y": 405.8868453461804
          },
          "lower_error_bar": {
            "x": 610.5105974309422,
            "y": 405.8868453461804
          }
        }
      ]
    }
  ]
}