{
  "image_file": "c25404ef-926a-48a3-8424-0ba645df1fb2.png",
  "model": "VQA-4bit-Fast",
  "error_bars": [
    {
      "lineName": "Pembrolizumab_200mg_QW",
      "points": [
        {
          "data_point": {
            "x": 144.20573316587095,
            "y": 54.671471669700395
          },
          "upper_error_bar": {
            "x": 144.20573316587095,
            "y": 53.0
          },
          "lower_error_bar": {
            "x": 144.20573316587095,
            "y": 439.0
          }
        },
        {
          "data_point": {
            "x": 488.9394560212728,
            "y": 260.89252953127135
          },
          "upper_error_bar": {
            "x": 488.9394560212728,
            "y": 200.0
          },
          "lower_error_bar": {
            "x": 488.9394560212728,
            "y": 439.0
          }
        },
        {
          "data_point": {
            "x": 490.4109047220311,
            "y": 261.6946784847031
          },
          "upper_error_bar": {
            "x": 490.4109047220311,
            "y": 200.0
          },
          "lower_error_bar": {
            "x": 490.4109047220311,
            "y": 328.0
          }
        },
        {
          "data_point": {
            "x": 502.86955130749425,
            "y": 268.37309690579787
          },
          "upper_error_bar": {
            "x": 502.86955130749425,
            "y": 243.74619381159573
          },
          "lower_error_bar": {
            "x": 502.86955130749425,
            "y": 439.0
          }
        },
        {
          "data_point": {
            "x": 511.3353166021926,
            "y": 272.797004443769
          },
          "upper_error_bar": {
            "x": 511.3353166021926,
            "y": 269.0
          },
          "lower_error_bar": {
            "x": 511.3353166021926,
            "y": 439.0
          }
        },
        {
          "data_point": {
            "x": 612.0836206032847,
            "y": 318.90754614673915
          },
          "upper_error_bar": {
            "x": 612.0836206032847,
            "y": 315.0
          },
          "lower_error_bar": {
            "x": 612.0836206032847,
            "y": 439.0
          }
        }
      ]
    },
    {
      "lineName": "Avelumab_10mg_kg_TrtA",
      "points": [
        {
          "data_point": {
            "x": 110.13975193973454,
            "y": 313.91849118050015
          },
          "upper_error_bar": {
            "x": 110.13975193973454,
            "y": 308.0
          },
          "lower_error_bar": {
            "x": 110.13975193973454,
            "y": 436.0
          }
        },
        {
          "data_point": {
            "x": 272.1117607179827,
            "y": 310.48407738651866
          },
          "upper_error_bar": {
            "x": 272.1117607179827,
            "y": 305.0
          },
          "lower_error_bar": {
            "x": 272.1117607179827,
            "y": 439.0
          }
        },
        {
          "data_point": {
            "x": 373.2998847950099,
            "y": 341.0759588927419
          },
          "upper_error_bar": {
            "x": 373.2998847950099,
            "y": 336.0
          },
          "lower_error_bar": {
            "x": 373.2998847950099,
            "y": 436.0
          }
        },
        {
          "data_point": {
            "x": 581.3471199427196,
            "y": 393.0404311411756
          },
          "upper_error_bar": {
            "x": 581.3471199427196,
            "y": 393.0404311411756
          },
          "lower_error_bar": {
            "x": 581.3471199427196,
            "y": 393.0404311411756
          }
        },
        {
          "data_point": {
            "x": 589.5214310654923,
            "y": 394.6661133228547
          },
          "upper_error_bar": {
            "x": 589.5214310654923,
            "y": 394.6661133228547
          },
          "lower_error_bar": {
            "x": 589.5214310654923,
            "y": 394.6661133228547
          }
        },
        {
          "data_point": {
            "x": 637.223106598261,
            "y": 403.59066979230425
          },
          "upper_error_bar": {
            "x": 637.223106598261,
            "y": 403.59066979230425
          },
          "lower_error_bar": {
            "x": 637.223106598261,
            "y": 403.59066979230425
          }
        }
      ]
    }
  ]
}