{
  "image_file": "ebe98dcf-41c6-4fb5-8fbe-3f726fbdb038.png",
  "model": "VQA-4bit-Fast",
  "error_bars": [
    {
      "lineName": "Ipilimumab_200mg_Q2W",
      "points": [
        {
          "data_point": {
            "x": 140.554898501109,
            "y": 93.08866544022226
          },
          "upper_error_bar": {
            "x": 140.554898501109,
            "y": 87.17733088044452
          },
          "lower_error_bar": {
            "x": 140.554898501109,
            "y": 181.0
          }
        },
        {
          "data_point": {
            "x": 161.50207495878266,
            "y": 94.12528685819427
          },
          "upper_error_bar": {
            "x": 161.50207495878266,
            "y": 93.0
          },
          "lower_error_bar": {
            "x": 161.50207495878266,
            "y": 183.0
          }
        },
        {
          "data_point": {
            "x": 172.53552414645867,
            "y": 100.50811861508271
          },
          "upper_error_bar": {
            "x": 172.53552414645867,
            "y": 68.01623723016542
          },
          "lower_error_bar": {
            "x": 172.53552414645867,
            "y": 166.0
          }
        },
        {
          "data_point": {
            "x": 190.55474453618137,
            "y": 115.31128141843612
          },
          "upper_error_bar": {
            "x": 190.55474453618137,
            "y": 115.0
          },
          "lower_error_bar": {
            "x": 190.55474453618137,
            "y": 213.0
          }
        },
        {
          "data_point": {
            "x": 195.14877608669622,
            "y": 119.60034663351917
          },
          "upper_error_bar": {
            "x": 195.14877608669622,
            "y": 119.60034663351917
          },
          "lower_error_bar": {
            "x": 195.14877608669622,
            "y": 119.60034663351917
          }
        },
        {
          "data_point": {
            "x": 202.35801872112833,
            "y": 126.57309643818621
          },
          "upper_error_bar": {
            "x": 202.35801872112833,
            "y": 126.57309643818621
          },
          "lower_error_bar": {
            "x": 202.35801872112833,
            "y": 126.57309643818621
          }
        },
        {
          "data_point": {
            "x": 216.53193821675626,
            "y": 140.76552731117067
          },
          "upper_error_bar": {
            "x": 216.53193821675626,
            "y": 44.0
          },
          "lower_error_bar": {
            "x": 216.53193821675626,
            "y": 145.0
          }
        },
        {
          "data_point": {
            "x": 237.06502456069273,
            "y": 161.49497390006854
          },
          "upper_error_bar": {
            "x": 237.06502456069273,
            "y": 161.49497390006854
          },
          "lower_error_bar": {
            "x": 237.06502456069273,
            "y": 161.49497390006854
          }
        },
        {
          "data_point": {
            "x": 265.60818004554733,
            "y": 189.09597345793486
          },
          "upper_error_bar": {
            "x": 265.60818004554733,
            "y": 189.09597345793486
          },
          "lower_error_bar": {
            "x": 265.60818004554733,
            "y": 189.09597345793486
          }
        },
        {
          "data_point": {
            "x": 286.7180883710708,
            "y": 208.04462332339494
          },
          "upper_error_bar": {
            "x": 286.7180883710708,
            "y": 208.04462332339494
          },
          "lower_error_bar": {
            "x": 286.7180883710708,
            "y": 208.04462332339494
          }
        },
        {
          "data_point": {
            "x": 298.8760498078871,
            "y": 218.3296992096739
          },
          "upper_error_bar": {
            "x": 298.8760498078871,
            "y": 218.3296992096739
          },
          "lower_error_bar": {
            "x": 298.8760498078871,
            "y": 218.3296992096739
          }
        },
        {
          "data_point": {
            "x": 301.2863503657769,
            "y": 220.3136435167914
          },
          "upper_error_bar": {
            "x": 301.2863503657769,
            "y": 220.3136435167914
          },
          "lower_error_bar": {
            "x": 301.2863503657769,
            "y": 220.3136435167914
          }
        }
      ]
    },
    {
      "lineName": "Panitumumab_200mg_Low",
      "points": [
        {
          "data_point": {
            "x": 95.24142666298343,
            "y": 245.13121900318774
          },
          "upper_error_bar": {
            "x": 95.24142666298343,
            "y": 245.13121900318774
          },
          "lower_error_bar": {
            "x": 95.24142666298343,
            "y": 245.13121900318774
          }
        },
        {
          "data_point": {
            "x": 104.60572793461793,
            "y": 199.4740642763137
          },
          "upper_error_bar": {
            "x": 104.60572793461793,
            "y": 199.4740642763137
          },
          "lower_error_bar": {
            "x": 104.60572793461793,
            "y": 199.4740642763137
          }
        },
        {
          "data_point": {
            "x": 144.69354476890618,
            "y": 156.08901532217453
          },
          "upper_error_bar": {
            "x": 144.69354476890618,
            "y": 87.0
          },
          "lower_error_bar": {
            "x": 144.69354476890618,
            "y": 170.0
          }
        },
        {
          "data_point": {
            "x": 175.88574412158982,
            "y": 176.67818468606163
          },
          "upper_error_bar": {
            "x": 175.88574412158982,
            "y": 133.0
          },
          "lower_error_bar": {
            "x": 175.88574412158982,
            "y": 187.35636937212325
          }
        },
        {
          "data_point": {
            "x": 180.45220847064343,
            "y": 180.56881975229874
          },
          "upper_error_bar": {
            "x": 180.45220847064343,
            "y": 115.0
          },
          "lower_error_bar": {
            "x": 180.45220847064343,
            "y": 213.0
          }
        },
        {
          "data_point": {
            "x": 235.3351456040304,
            "y": 227.92778461124112
          },
          "upper_error_bar": {
            "x": 235.3351456040304,
            "y": 227.92778461124112
          },
          "lower_error_bar": {
            "x": 235.3351456040304,
            "y": 227.92778461124112
          }
        },
        {
          "data_point": {
            "x": 235.74850392728393,
            "y": 228.26319346058176
          },
          "upper_error_bar": {
            "x": 235.74850392728393,
            "y": 228.26319346058176
          },
          "lower_error_bar": {
            "x": 235.74850392728393,
            "y": 228.26319346058176
          }
        },
        {
          "data_point": {
            "x": 303.93554059486655,
            "y": 276.9629662354299
          },
          "upper_error_bar": {
            "x": 303.93554059486655,
            "y": 276.9629662354299
          },
          "lower_error_bar": {
            "x": 303.93554059486655,
            "y": 276.9629662354299
          }
        },
        {
          "data_point": {
            "x": 319.1694218012495,
            "y": 286.12718222520647
          },
          "upper_error_bar": {
            "x": 319.1694218012495,
            "y": 286.12718222520647
          },
          "lower_error_bar": {
            "x": 319.1694218012495,
            "y": 286.12718222520647
          }
        },
        {
          "data_point": {
            "x": 520.8308531829261,
            "y": 365.5687790406114
          },
          "upper_error_bar": {
            "x": 520.8308531829261,
            "y": 365.5687790406114
          },
          "lower_error_bar": {
            "x": 520.8308531829261,
            "y": 365.5687790406114
          }
        },
        {
          "data_point": {
            "x": 581.2204624397792,
            "y": 378.9613053037856
          },
          "upper_error_bar": {
            "x": 581.2204624397792,
            "y": 378.9613053037856
          },
          "lower_error_bar": {
            "x": 581.2204624397792,
            "y": 378.9613053037856
          }
        },
        {
          "data_point": {
            "x": 631.1091270584906,
            "y": 387.73951887859175
          },
          "upper_error_bar": {
            "x": 631.1091270584906,
            "y": 387.73951887859175
          },
          "lower_error_bar": {
            "x": 631.1091270584906,
            "y": 387.73951887859175
          }
        }
      ]
    },
    {
      "lineName": "Panitumumab_0.1mg_kg_BID",
      "points": [
        {
          "data_point": {
            "x": 99.32846039962236,
            "y": 335.6385736107258
          },
          "upper_error_bar": {
            "x": 99.32846039962236,
            "y": 335.6385736107258
          },
          "lower_error_bar": {
            "x": 99.32846039962236,
            "y": 335.6385736107258
          }
        },
        {
          "data_point": {
            "x": 117.5402466720738,
            "y": 302.1402742139391
          },
          "upper_error_bar": {
            "x": 117.5402466720738,
            "y": 302.1402742139391
          },
          "lower_error_bar": {
            "x": 117.5402466720738,
            "y": 302.1402742139391
          }
        },
        {
          "data_point": {
            "x": 135.9056799931363,
            "y": 289.99545248107313
          },
          "upper_error_bar": {
            "x": 135.9056799931363,
            "y": 99.0
          },
          "lower_error_bar": {
            "x": 135.9056799931363,
            "y": 398.99090496214626
          }
        },
        {
          "data_point": {
            "x": 143.05223414111578,
            "y": 288.9019285942742
          },
          "upper_error_bar": {
            "x": 143.05223414111578,
            "y": 87.0
          },
          "lower_error_bar": {
            "x": 143.05223414111578,
            "y": 407.80385718854836
          }
        },
        {
          "data_point": {
            "x": 258.16451709679353,
            "y": 343.060601590604
          },
          "upper_error_bar": {
            "x": 258.16451709679353,
            "y": 343.060601590604
          },
          "lower_error_bar": {
            "x": 258.16451709679353,
            "y": 343.060601590604
          }
        },
        {
          "data_point": {
            "x": 294.29429820747924,
            "y": 360.00963389051606
          },
          "upper_error_bar": {
            "x": 294.29429820747924,
            "y": 360.00963389051606
          },
          "lower_error_bar": {
            "x": 294.29429820747924,
            "y": 360.00963389051606
          }
        },
        {
          "data_point": {
            "x": 294.7760781665318,
            "y": 360.2142379898986
          },
          "upper_error_bar": {
            "x": 294.7760781665318,
            "y": 360.2142379898986
          },
          "lower_error_bar": {
            "x": 294.7760781665318,
            "y": 360.2142379898986
          }
        },
        {
          "data_point": {
            "x": 301.0552698044613,
            "y": 362.8301814963943
          },
          "upper_error_bar": {
            "x": 301.0552698044613,
            "y": 362.8301814963943
          },
          "lower_error_bar": {
            "x": 301.0552698044613,
            "y": 362.8301814963943
          }
        },
        {
          "data_point": {
            "x": 311.1267426470663,
            "y": 366.8322731265362
          },
          "upper_error_bar": {
            "x": 311.1267426470663,
            "y": 366.8322731265362
          },
          "lower_error_bar": {
            "x": 311.1267426470663,
            "y": 366.8322731265362
          }
        },
        {
          "data_point": {
            "x": 389.65191026644567,
            "y": 390.85179958455166
          },
          "upper_error_bar": {
            "x": 389.65191026644567,
            "y": 390.85179958455166
          },
          "lower_error_bar": {
            "x": 389.65191026644567,
            "y": 390.85179958455166
          }
        },
        {
          "data_point": {
            "x": 438.52312305807123,
            "y": 400.75885806965255
          },
          "upper_error_bar": {
            "x": 438.52312305807123,
            "y": 400.75885806965255
          },
          "lower_error_bar": {
            "x": 438.52312305807123,
            "y": 400.75885806965255
          }
        },
        {
          "data_point": {
            "x": 520.7335518899015,
            "y": 411.7366717239549
          },
          "upper_error_bar": {
            "x": 520.7335518899015,
            "y": 411.7366717239549
          },
          "lower_error_bar": {
            "x": 520.7335518899015,
            "y": 411.7366717239549
          }
        },
        {
          "data_point": {
            "x": 626.9322749113676,
            "y": 419.475646386138
          },
          "upper_error_bar": {
            "x": 626.9322749113676,
            "y": 419.475646386138
          },
          "lower_error_bar": {
            "x": 626.9322749113676,
            "y": 419.475646386138
          }
        }
      ]
    }
  ]
}