{
  "image_file": "16be86ca-4f60-4a22-ae83-662fdabf2eb2.png",
  "error_bars": [
    {
      "lineName": "BNP_CohortA",
      "points": [
        {
          "data_point": {
            "x": 135.9942019584756,
            "y": 392.5117276022566
          },
          "upper_error_bar": {
            "x": 135.9942019584756,
            "y": 332.0
          },
          "lower_error_bar": {
            "x": 135.9942019584756,
            "y": 438.0
          }
        },
        {
          "data_point": {
            "x": 201.1792447331497,
            "y": 298.4336853928838
          },
          "upper_error_bar": {
            "x": 201.1792447331497,
            "y": 264.0
          },
          "lower_error_bar": {
            "x": 201.1792447331497,
            "y": 438.0
          }
        },
        {
          "data_point": {
            "x": 272.4272683222267,
            "y": 222.51068942416748
          },
          "upper_error_bar": {
            "x": 272.4272683222267,
            "y": 140.0
          },
          "lower_error_bar": {
            "x": 272.4272683222267,
            "y": 371.0
          }
        },
        {
          "data_point": {
            "x": 331.81013667116235,
            "y": 175.27351363869423
          },
          "upper_error_bar": {
            "x": 331.81013667116235,
            "y": 103.0
          },
          "lower_error_bar": {
            "x": 331.81013667116235,
            "y": 324.0
          }
        },
        {
          "data_point": {
            "x": 386.92527278644513,
            "y": 141.3180423981936
          },
          "upper_error_bar": {
            "x": 386.92527278644513,
            "y": 137.0
          },
          "lower_error_bar": {
            "x": 386.92527278644513,
            "y": 290.0
          }
        },
        {
          "data_point": {
            "x": 424.3343458067396,
            "y": 122.59033106090658
          },
          "upper_error_bar": {
            "x": 424.3343458067396,
            "y": 9.0
          },
          "lower_error_bar": {
            "x": 424.3343458067396,
            "y": 271.0
          }
        },
        {
          "data_point": {
            "x": 594.7758707788195,
            "y": 67.65911084641436
          },
          "upper_error_bar": {
            "x": 594.7758707788195,
            "y": 40.0
          },
          "lower_error_bar": {
            "x": 594.7758707788195,
            "y": 216.0
          }
        },
        {
          "data_point": {
            "x": 623.5159060512665,
            "y": 61.85316438800123
          },
          "upper_error_bar": {
            "x": 623.5159060512665,
            "y": 30.0
          },
          "lower_error_bar": {
            "x": 623.5159060512665,
            "y": 210.0
          }
        }
      ]
    }
  ]
}