{
  "image_file": "82f52ef8-f8c3-4d21-b537-d1a29f0f15cd.png",
  "error_bars": [
    {
      "lineName": "Cetuximab_100mg_CohortB",
      "points": [
        {
          "data_point": {
            "x": 119.3197704326166,
            "y": 67.51015752360581
          },
          "upper_error_bar": {
            "x": 119.3197704326166,
            "y": 51.0
          },
          "lower_error_bar": {
            "x": 119.3197704326166,
            "y": 153.0
          }
        },
        {
          "data_point": {
            "x": 177.81967719076937,
            "y": 83.34812622147575
          },
          "upper_error_bar": {
            "x": 177.81967719076937,
            "y": 83.34812622147575
          },
          "lower_error_bar": {
            "x": 177.81967719076937,
            "y": 83.34812622147575
          }
        },
        {
          "data_point": {
            "x": 233.91578180450193,
            "y": 134.6604128230262
          },
          "upper_error_bar": {
            "x": 233.91578180450193,
            "y": 123.0
          },
          "lower_error_bar": {
            "x": 233.91578180450193,
            "y": 193.0
          }
        },
        {
          "data_point": {
            "x": 299.2518543733294,
            "y": 197.45779763167775
          },
          "upper_error_bar": {
            "x": 299.2518543733294,
            "y": 186.0
          },
          "lower_error_bar": {
            "x": 299.2518543733294,
            "y": 225.0
          }
        },
        {
          "data_point": {
            "x": 322.1453564706831,
            "y": 217.74673505397817
          },
          "upper_error_bar": {
            "x": 322.1453564706831,
            "y": 176.0
          },
          "lower_error_bar": {
            "x": 322.1453564706831,
            "y": 269.0
          }
        },
        {
          "data_point": {
            "x": 324.72510082214217,
            "y": 219.96059871998767
          },
          "upper_error_bar": {
            "x": 324.72510082214217,
            "y": 176.0
          },
          "lower_error_bar": {
            "x": 324.72510082214217,
            "y": 269.0
          }
        },
        {
          "data_point": {
            "x": 382.41137492744826,
            "y": 265.4937961750069
          },
          "upper_error_bar": {
            "x": 382.41137492744826,
            "y": 254.0
          },
          "lower_error_bar": {
            "x": 382.41137492744826,
            "y": 272.0
          }
        },
        {
          "data_point": {
            "x": 441.65498945092094,
            "y": 304.63589348473397
          },
          "upper_error_bar": {
            "x": 441.65498945092094,
            "y": 293.0
          },
          "lower_error_bar": {
            "x": 441.65498945092094,
            "y": 349.0
          }
        },
        {
          "data_point": {
            "x": 450.57480667342537,
            "y": 309.9149459207941
          },
          "upper_error_bar": {
            "x": 450.57480667342537,
            "y": 309.9149459207941
          },
          "lower_error_bar": {
            "x": 450.57480667342537,
            "y": 309.9149459207941
          }
        },
        {
          "data_point": {
            "x": 561.391649240864,
            "y": 364.16402962282757
          },
          "upper_error_bar": {
            "x": 561.391649240864,
            "y": 253.0
          },
          "lower_error_bar": {
            "x": 561.391649240864,
            "y": 449.0
          }
        },
        {
          "data_point": {
            "x": 637.1660309861068,
            "y": 391.37904105767075
          },
          "upper_error_bar": {
            "x": 637.1660309861068,
            "y": 253.0
          },
          "lower_error_bar": {
            "x": 637.1660309861068,
            "y": 427.0
          }
        }
      ]
    }
  ]
}